casual_mcp_server_words/__init__.py
casual_mcp_server_words/cli.py
casual_mcp_server_words/server.py
casual_mcp_server_words-1.0.1.dist-info/METADATA
casual_mcp_server_words-1.0.1.dist-info/WHEEL
casual_mcp_server_words-1.0.1.dist-info/entry_points.txt
casual_mcp_server_words-1.0.1.dist-info/top_level.txt
casual_mcp_server_words-1.0.1.dist-info/RECORD
