Metadata-Version: 2.4
Name: casual-mcp-server-words
Version: 1.0.1
Summary: Dictionary and thesaurus utilities as an MCP server
Author: Alex Stansfield
License: MIT
Project-URL: Homepage, https://github.com/casualgenius/mcp-servers
Project-URL: Issues, https://github.com/casualgenius/mcp-servers/issues
Project-URL: Source, https://github.com/casualgenius/mcp-servers
Requires-Python: >=3.10
Requires-Dist: fastmcp
Requires-Dist: pydantic
Requires-Dist: requests
